{
  "coord": {
    "lon": 51.4215,
    "lat": 35.6944
  },
  "weather": [
    {
      "id": 800,
      "main": "Clear",
      "description": "clear sky",
      "icon": "01d"
    }
  ],
  "base": "stations",
  "main": {
    "temp": 24.84,
    "feels_like": 23.98,
    "temp_min": 24.84,
    "temp_max": 24.84,
    "pressure": 1013,
    "humidity": 23,
    "sea_level": 1013,
    "grnd_level": 864
  },
  "visibility": 10000,
  "wind": {
    "speed": 2.68,
    "deg": 340
  },
  "clouds": {
    "all": 1
  },
  "dt": 1781063877,
  "sys": {
    "type": 2,
    "id": 47737,
    "country": "IR",
    "sunrise": 1781054288,
    "sunset": 1781106570
  },
  "timezone": 12600,
  "id": 112931,
  "name": "Tehran",
  "cod": 200,
  "_last_updated_utc": "2026-06-10T03:59:09.770Z"
}